memtab/__init__.py
memtab/categorizer.py
memtab/cli.py
memtab/memtab.py
memtab/models.py
memtab/py.typed
memtab/viz.py
memtab/vizhookspecs.py
memtab/parsers/__init__.py
memtab/parsers/base.py
memtab/parsers/map.py
memtab/parsers/nm.py
memtab/parsers/objdump.py
memtab/parsers/readelf.py
memtab/parsers/size.py
memtab/schemas/memtab_config_file_schema.json
memtab/schemas/memtab_config_schema.json
memtab/schemas/memtab_schema.json
memtab-1.0.7.dist-info/METADATA
memtab-1.0.7.dist-info/WHEEL
memtab-1.0.7.dist-info/entry_points.txt
memtab-1.0.7.dist-info/licenses/LICENSE.md
memtab-1.0.7.dist-info/RECORD
