Metadata-Version: 2.4
Name: memtab
Version: 1.0.7
Summary: ELF File Memory Tabulator
Project-URL: Bug Tracker, https://github.com/etn-corp/memtab/issues
License-File: LICENSE.md
Classifier: Development Status :: 4 - Beta
Classifier: Environment :: Console
Classifier: Intended Audience :: Developers
Classifier: License :: OSI Approved :: MIT License
Classifier: Topic :: Software Development :: Build Tools
Classifier: Topic :: Software Development :: Embedded Systems
Requires-Python: >=3.9
Requires-Dist: appdirs==1.4.4
Requires-Dist: gitpython>=3.1.44
Requires-Dist: jsonschema>=4.23.0
Requires-Dist: mdutils>=1.6.0
Requires-Dist: pandas[excel]>=2.2
Requires-Dist: pluggy>=1.5.0
Requires-Dist: pyelftools>=0.32
Requires-Dist: python-dotenv>=1.0.1
Requires-Dist: pyyaml>=6.0.2
Requires-Dist: tabulate>=0.9.0
Requires-Dist: typer>=0.15.1
